dface/__init__.py
dface/facenet.py
dface/mtcnn.py
dface-1.1.5.dist-info/LICENSE
dface-1.1.5.dist-info/METADATA
dface-1.1.5.dist-info/WHEEL
dface-1.1.5.dist-info/top_level.txt
dface-1.1.5.dist-info/RECORD
