Metadata-Version: 2.1
Name: dface
Version: 1.1.5
Summary: Face detection and recognition library that focuses on speed and ease of use.
Home-page: https://github.com/deepware/dface
Author: deepware
Author-email: dogan.kurt@dodobyte.com
License: UNKNOWN
Platform: UNKNOWN
Classifier: Programming Language :: Python :: 3
Classifier: License :: OSI Approved :: BSD License
Classifier: Operating System :: OS Independent
